<las2peer:consent>
	<consentLevel>
		<name>Basic Moodle Data</name>
		<level>1</level>
		<functions>
			<function>completed</function>
			<function>received</function>
			<function>submitted</function>
			<function>answered</function>
		</functions>
		<services>
			<service>Moodle</service>
		</services>
	</consentLevel>
	
	<consentLevel>
		<name>All Moodle Data</name>
		<level>2</level>
		<functions>
			<function>completed</function>
			<function>received</function>
			<function>posted</function>
			<function>replied</function>
			<function>submitted</function>
			<function>created</function>
			<function>answered</function>
			<function>viewed</function>
		</functions>
		<services>
			<service>Moodle</service>
		</services>
	</consentLevel>
</las2peer:consent>